main.py
goldens_rule-0.1.0.dist-info/METADATA
goldens_rule-0.1.0.dist-info/WHEEL
goldens_rule-0.1.0.dist-info/top_level.txt
goldens_rule-0.1.0.dist-info/RECORD
